Workbook

Sheet Order_items
A1: order_item_id | B1: order_id | C1: product_id | D1: quantity | E1: unit_price | F1: Total revenue
A2: 1 | B2: 1 | C2: 163 | D2: 1 | E2: 193.8 | F2: =E2*D2 -> 193.8
A3: 2 | B3: 1 | C3: 156 | D3: 2 | E3: 395.52 | F3: =E3*D3 -> 791.04
A4: 3 | B4: 1 | C4: 43 | D4: 2 | E4: 1153.5 | F4: =E4*D4 -> 2307
A5: 4 | B5: 2 | C5: 153 | D5: 1 | E5: 318.02 | F5: =E5*D5 -> 318.02
A6: 5 | B6: 2 | C6: 121 | D6: 1 | E6: 159.37 | F6: =E6*D6 -> 159.37
A7: 6 | B7: 2 | C7: 138 | D7: 1 | E7: 280.61 | F7: =E7*D7 -> 280.61
A8: 7 | B8: 3 | C8: 27 | D8: 1 | E8: 628.59 | F8: =E8*D8 -> 628.59
A9: 8 | B9: 3 | C9: 103 | D9: 1 | E9: 228.45 | F9: =E9*D9 -> 228.45
A10: 9 | B10: 3 | C10: 160 | D10: 1 | E10: 196.53 | F10: =E10*D10 -> 196.53
A11: 10 | B11: 4 | C11: 19 | D11: 2 | E11: 968.43 | F11: =E11*D11 -> 1936.86
A12: 11 | B12: 5 | C12: 172 | D12: 1 | E12: 315.29 | F12: =E12*D12 -> 315.29
A13: 12 | B13: 6 | C13: 102 | D13: 1 | E13: 579.6 | F13: =E13*D13 -> 579.6
... A9037: 9036 | B9037: 5000 | C9037: 53 | D9037: 2 | E9037: 912.95 | F9037: =E9037*D9037 -> 1825.9

Sheet Basic statistics
A3: Row Labels | B3: Sum of Total revenue | E3: Mean
A4: 1 | B4: 3291.84 | D4: 3291.84 | E4: =AVERAGE(B:B) -> 2725.0102
A5: 2 | B5: 758 | D5: 758
A6: 3 | B6: 1053.57 | D6: 1053.57 | E6: Median
A7: 4 | B7: 1936.86 | D7: 1936.86 | E7: =MEDIAN(B:B) -> 1052.58
A8: 5 | B8: 315.29 | D8: 315.29
A9: 6 | B9: 1125.06 | D9: 1125.06 | E9: Standard deviation
A10: 7 | B10: 2036.83 | D10: 2036.83 | E10: =_xlfn.STDEV.P(B4:B5003) -> 1162.4566
A11: 8 | B11: 888.69 | D11: 888.69
A12: 9 | B12: 3274.8 | D12: 3274.8
A13: 10 | B13: 2931.18 | D13: 2931.18
A14: 11 | B14: 1217.05 | D14: 1217.05
A15: 12 | B15: 1082.75 | D15: 1082.75
A16: 13 | B16: 256.17 | D16: 256.17
A17: 14 | B17: 827.49 | D17: 827.49
A18: 15 | B18: 1814.82 | D18: 1814.82
A19: 16 | B19: 329.52 | D19: 329.52
A20: 17 | B20: 274.33 | D20: 274.33
A21: 18 | B21: 966.66 | D21: 966.66
A22: 19 | B22: 2337.54 | D22: 2337.54
... A5003: 5000 | B5003: 2575.5 | D5003: 2575.5
A5004: Grand Total | B5004: 6813888

Sheet Customer table
A1: customer_id | B1: first_name | C1: last_name | D1: email | E1: registration_date | F1: region | G1: customer_segment | H1: Email
A2: 1 | B2: Jessica | C2: Brown | D2: jessica.brown1@email.com | E2: 45112 | F2: West | G2: Occasional | H2: =IF(OR(G2="Regular",G2="VIP"),"Email user","Non email user") -> Non email user
A3: 2 | B3: Susan | C3: Garcia | D3: susan.garcia2@email.com | E3: 45260 | F3: East | G3: Occasional | H3: =IF(OR(G3="Regular",G3="VIP"),"Email user","Non email user") -> Non email user
A4: 3 | B4: Sarah | C4: Thomas | D4: sarah.thomas3@email.com | E4: 45230 | F4: East | G4: Regular | H4: =IF(OR(G4="Regular",G4="VIP"),"Email user","Non email user") -> Email user
A5: 4 | B5: Linda | C5: Williams | D5: linda.williams4@email.com | E5: 45234 | F5: South | G5: Occasional | H5: =IF(OR(G5="Regular",G5="VIP"),"Email user","Non email user") -> Non email user
A6: 5 | B6: Charles | C6: Martin | D6: charles.martin5@email.com | E6: 45099 | F6: North | G6: Occasional | H6: =IF(OR(G6="Regular",G6="VIP"),"Email user","Non email user") -> Non email user
A7: 6 | B7: David | C7: Garcia | D7: david.garcia6@email.com | E7: 45108 | F7: East | G7: Regular | H7: =IF(OR(G7="Regular",G7="VIP"),"Email user","Non email user") -> Email user
A8: 7 | B8: Karen | C8: White | D8: karen.white7@email.com | E8: 45211 | F8: North | G8: Occasional | H8: =IF(OR(G8="Regular",G8="VIP"),"Email user","Non email user") -> Non email user
A9: 8 | B9: Michael | C9: Williams | D9: michael.williams8@email.com | E9: 45239 | F9: West | G9: Occasional | H9: =IF(OR(G9="Regular",G9="VIP"),"Email user","Non email user") -> Non email user
A10: 9 | B10: Linda | C10: White | D10: linda.white9@email.com | E10: 45291 | F10: West | G10: Occasional | H10: =IF(OR(G10="Regular",G10="VIP"),"Email user","Non email user") -> Non email user
A11: 10 | B11: James | C11: Williams | D11: james.williams10@email.com | E11: 45240 | F11: South | G11: Regular | H11: =IF(OR(G11="Regular",G11="VIP"),"Email user","Non email user") -> Email user
A12: 11 | B12: Charles | C12: Lopez | D12: charles.lopez11@email.com | E12: 45198 | F12: East | G12: Occasional | H12: =IF(OR(G12="Regular",G12="VIP"),"Email user","Non email user") -> Non email user
A13: 12 | B13: Lisa | C13: Moore | D13: lisa.moore12@email.com | E13: 45202 | F13: West | G13: Regular | H13: =IF(OR(G13="Regular",G13="VIP"),"Email user","Non email user") -> Email user
... A10001: 10000 | B10001: Charles | C10001: Miller | D10001: charles.miller10000@email.com | E10001: 45232 | F10001: West | G10001: Occasional | H10001: =IF(OR(G10001="Regular",G10001="VIP"),"Email user","Non email user") -> Non email user

Sheet Test 1
A1: order_item_id | B1: order_id | C1: product_id | D1: quantity | E1: unit_price | F1: Total revenue | G1: customer_id | H1: email | J1: TYPE | K1: Average revenue | M1: EMAIL USER | N1: NON EMAIL USER
A2: 1 | B2: 1 | C2: 163 | D2: 1 | E2: 193.8 | F2: =E2*D2 -> 193.8 | G2: 1 | H2: =VLOOKUP(G2,'Customer table'!A:H,8,FALSE) -> Non email user | J2: Email user | K2: =AVERAGEIF(H:H,"email user",F:F) -> 756.48732 | M2: {=_xlfn._xlws.FILTER(F2:F9037,H2:H9037="Email user")} -> 2307 | N2: {=_xlfn._xlws.FILTER(F2:F9037,H2:H9037="non email user")} -> 193.8
A3: 2 | B3: 1 | C3: 156 | D3: 2 | E3: 395.52 | F3: =E3*D3 -> 791.04 | G3: 2 | H3: =VLOOKUP(G3,'Customer table'!A:H,8,FALSE) -> Non email user | J3: Non email user | K3: =AVERAGEIF(H:H,"non email user",F:F) -> 752.81089 | M3: 280.61 | N3: 791.04
A4: 3 | B4: 1 | C4: 43 | D4: 2 | E4: 1153.5 | F4: =E4*D4 -> 2307 | G4: 3 | H4: =VLOOKUP(G4,'Customer table'!A:H,8,FALSE) -> Email user | M4: 1936.86 | N4: 318.02
A5: 4 | B5: 2 | C5: 153 | D5: 1 | E5: 318.02 | F5: =E5*D5 -> 318.02 | G5: 4 | H5: =VLOOKUP(G5,'Customer table'!A:H,8,FALSE) -> Non email user | M5: 579.6 | N5: 159.37
A6: 5 | B6: 2 | C6: 121 | D6: 1 | E6: 159.37 | F6: =E6*D6 -> 159.37 | G6: 5 | H6: =VLOOKUP(G6,'Customer table'!A:H,8,FALSE) -> Non email user | J6: T-TEST Result | M6: 545.46 | N6: 628.59
A7: 6 | B7: 2 | C7: 138 | D7: 1 | E7: 280.61 | F7: =E7*D7 -> 280.61 | G7: 6 | H7: =VLOOKUP(G7,'Customer table'!A:H,8,FALSE) -> Email user | J7: =_xlfn.T.TEST(M2:M9037,N2:N9037,2,2) -> 0.81279997 | M7: 884.91 | N7: 228.45
A8: 7 | B8: 3 | C8: 27 | D8: 1 | E8: 628.59 | F8: =E8*D8 -> 628.59 | G8: 7 | H8: =VLOOKUP(G8,'Customer table'!A:H,8,FALSE) -> Non email user | M8: 826.16 | N8: 196.53
A9: 8 | B9: 3 | C9: 103 | D9: 1 | E9: 228.45 | F9: =E9*D9 -> 228.45 | G9: 8 | H9: =VLOOKUP(G9,'Customer table'!A:H,8,FALSE) -> Non email user | M9: 325.76 | N9: 315.29
A10: 9 | B10: 3 | C10: 160 | D10: 1 | E10: 196.53 | F10: =E10*D10 -> 196.53 | G10: 9 | H10: =VLOOKUP(G10,'Customer table'!A:H,8,FALSE) -> Non email user | M10: 256.68 | N10: 264.46
A11: 10 | B11: 4 | C11: 19 | D11: 2 | E11: 968.43 | F11: =E11*D11 -> 1936.86 | G11: 10 | H11: =VLOOKUP(G11,'Customer table'!A:H,8,FALSE) -> Email user | M11: 367.55 | N11: 1816.72
A12: 11 | B12: 5 | C12: 172 | D12: 1 | E12: 315.29 | F12: =E12*D12 -> 315.29 | G12: 11 | H12: =VLOOKUP(G12,'Customer table'!A:H,8,FALSE) -> Non email user | M12: 265.95 | N12: 296.31
A13: 12 | B13: 6 | C13: 102 | D13: 1 | E13: 579.6 | F13: =E13*D13 -> 579.6 | G13: 12 | H13: =VLOOKUP(G13,'Customer table'!A:H,8,FALSE) -> Email user | M13: 401.39 | N13: 895.82
A14: 13 | B14: 6 | C14: 31 | D14: 1 | E14: 545.46 | F14: =E14*D14 -> 545.46 | G14: 13 | H14: =VLOOKUP(G14,'Customer table'!A:H,8,FALSE) -> Email user | M14: 1096.78 | N14: 485.89
A15: 14 | B15: 7 | C15: 115 | D15: 1 | E15: 884.91 | F15: =E15*D15 -> 884.91 | G15: 14 | H15: =VLOOKUP(G15,'Customer table'!A:H,8,FALSE) -> Email user | M15: 941.99 | N15: 1883.98
A16: 15 | B16: 7 | C16: 193 | D16: 2 | E16: 413.08 | F16: =E16*D16 -> 826.16 | G16: 15 | H16: =VLOOKUP(G16,'Customer table'!A:H,8,FALSE) -> Email user | M16: 623.01 | N16: 159.92
A17: 16 | B17: 7 | C17: 178 | D17: 1 | E17: 325.76 | F17: =E17*D17 -> 325.76 | G17: 16 | H17: =VLOOKUP(G17,'Customer table'!A:H,8,FALSE) -> Email user | M17: 274.33 | N17: 120.27
A18: 17 | B18: 8 | C18: 157 | D18: 1 | E18: 256.68 | F18: =E18*D18 -> 256.68 | G18: 17 | H18: =VLOOKUP(G18,'Customer table'!A:H,8,FALSE) -> Email user | M18: 966.66 | N18: 140.76
A19: 18 | B19: 8 | C19: 175 | D19: 1 | E19: 367.55 | F19: =E19*D19 -> 367.55 | G19: 18 | H19: =VLOOKUP(G19,'Customer table'!A:H,8,FALSE) -> Email user | M19: 965.83 | N19: 256.17
... A3126: 3125 | B3126: 1719 | C3126: 16 | D3126: 1 | E3126: 1435.99 | F3126: =E3126*D3126 -> 1435.99 | G3126: 3125 | H3126: =VLOOKUP(G3126,'Customer table'!A:H,8,FALSE) -> Non email user | M3126: 749.6 | N3126: 319.84
A3127: 3126 | B3127: 1720 | C3127: 188 | D3127: 1 | E3127: 150.49 | F3127: =E3127*D3127 -> 150.49 | G3127: 3126 | H3127: =VLOOKUP(G3127,'Customer table'!A:H,8,FALSE) -> Email user | N3127: 1129.1
A3128: 3127 | B3128: 1720 | C3128: 128 | D3128: 1 | E3128: 257.24 | F3128: =E3128*D3128 -> 257.24 | G3128: 3127 | H3128: =VLOOKUP(G3128,'Customer table'!A:H,8,FALSE) -> Non email user | N3128: 413.05
A3129: 3128 | B3129: 1721 | C3129: 199 | D3129: 1 | E3129: 364.61 | F3129: =E3129*D3129 -> 364.61 | G3129: 3128 | H3129: =VLOOKUP(G3129,'Customer table'!A:H,8,FALSE) -> Email user | N3129: 204.06
A3130: 3129 | B3130: 1721 | C3130: 165 | D3130: 2 | E3130: 331.33 | F3130: =E3130*D3130 -> 662.66 | G3130: 3129 | H3130: =VLOOKUP(G3130,'Customer table'!A:H,8,FALSE) -> Email user | N3130: 352.84
A3131: 3130 | B3131: 1721 | C3131: 196 | D3131: 1 | E3131: 140.76 | F3131: =E3131*D3131 -> 140.76 | G3131: 3130 | H3131: =VLOOKUP(G3131,'Customer table'!A:H,8,FALSE) -> Non email user | N3131: 290.79
A3132: 3131 | B3132: 1721 | C3132: 41 | D3132: 3 | E3132: 1041.67 | F3132: =E3132*D3132 -> 3125.01 | G3132: 3131 | H3132: =VLOOKUP(G3132,'Customer table'!A:H,8,FALSE) -> Email user | N3132: 744.5
A3133: 3132 | B3133: 1722 | C3133: 82 | D3133: 2 | E3133: 966.66 | F3133: =E3133*D3133 -> 1933.32 | G3133: 3132 | H3133: =VLOOKUP(G3133,'Customer table'!A:H,8,FALSE) -> Email user | N3133: 275.86
A3134: 3133 | B3134: 1723 | C3134: 113 | D3134: 1 | E3134: 901.51 | F3134: =E3134*D3134 -> 901.51 | G3134: 3133 | H3134: =VLOOKUP(G3134,'Customer table'!A:H,8,FALSE) -> Non email user | N3134: 196.53
A3135: 3134 | B3135: 1724 | C3135: 39 | D3135: 1 | E3135: 1791.45 | F3135: =E3135*D3135 -> 1791.45 | G3135: 3134 | H3135: =VLOOKUP(G3135,'Customer table'!A:H,8,FALSE) -> Email user | N3135: 1995.72
A3136: 3135 | B3136: 1725 | C3136: 85 | D3136: 1 | E3136: 359.28 | F3136: =E3136*D3136 -> 359.28 | G3136: 3135 | H3136: =VLOOKUP(G3136,'Customer table'!A:H,8,FALSE) -> Non email user | N3136: 323.68
A3137: 3136 | B3137: 1725 | C3137: 3 | D3137: 2 | E3137: 539.1 | F3137: =E3137*D3137 -> 1078.2 | G3137: 3136 | H3137: =VLOOKUP(G3137,'Customer table'!A:H,8,FALSE) -> Non email user | N3137: 318.02
A3138: 3137 | B3138: 1725 | C3138: 185 | D3138: 1 | E3138: 189.69 | F3138: =E3138*D3138 -> 189.69 | G3138: 3137 | H3138: =VLOOKUP(G3138,'Customer table'!A:H,8,FALSE) -> Non email user | N3138: 1257.96
... A5912: 5911 | B5912: 3277 | C5912: 192 | D5912: 1 | E5912: 485.89 | F5912: =E5912*D5912 -> 485.89 | G5912: 5911 | H5912: =VLOOKUP(G5912,'Customer table'!A:H,8,FALSE) -> Non email user | N5912: 1825.9
A5913: 5912 | B5913: 3278 | C5913: 136 | D5913: 1 | E5913: 276.75 | F5913: =E5913*D5913 -> 276.75 | G5913: 5912 | H5913: =VLOOKUP(G5913,'Customer table'!A:H,8,FALSE) -> Non email user
A5914: 5913 | B5914: 3279 | C5914: 17 | D5914: 1 | E5914: 1786.37 | F5914: =E5914*D5914 -> 1786.37 | G5914: 5913 | H5914: =VLOOKUP(G5914,'Customer table'!A:H,8,FALSE) -> Non email user
A5915: 5914 | B5915: 3280 | C5915: 180 | D5915: 1 | E5915: 204.06 | F5915: =E5915*D5915 -> 204.06 | G5915: 5914 | H5915: =VLOOKUP(G5915,'Customer table'!A:H,8,FALSE) -> Non email user
A5916: 5915 | B5916: 3281 | C5916: 72 | D5916: 1 | E5916: 366.31 | F5916: =E5916*D5916 -> 366.31 | G5916: 5915 | H5916: =VLOOKUP(G5916,'Customer table'!A:H,8,FALSE) -> Non email user
A5917: 5916 | B5917: 3281 | C5917: 8 | D5917: 1 | E5917: 1517.02 | F5917: =E5917*D5917 -> 1517.02 | G5917: 5916 | H5917: =VLOOKUP(G5917,'Customer table'!A:H,8,FALSE) -> Non email user
A5918: 5917 | B5918: 3282 | C5918: 98 | D5918: 1 | E5918: 941.99 | F5918: =E5918*D5918 -> 941.99 | G5918: 5917 | H5918: =VLOOKUP(G5918,'Customer table'!A:H,8,FALSE) -> Email user
A5919: 5918 | B5919: 3282 | C5919: 29 | D5919: 1 | E5919: 1732.64 | F5919: =E5919*D5919 -> 1732.64 | G5919: 5918 | H5919: =VLOOKUP(G5919,'Customer table'!A:H,8,FALSE) -> Non email user
A5920: 5919 | B5920: 3283 | C5920: 134 | D5920: 2 | E5920: 260.57 | F5920: =E5920*D5920 -> 521.14 | G5920: 5919 | H5920: =VLOOKUP(G5920,'Customer table'!A:H,8,FALSE) -> Non email user
A5921: 5920 | B5921: 3283 | C5921: 160 | D5921: 1 | E5921: 196.53 | F5921: =E5921*D5921 -> 196.53 | G5921: 5920 | H5921: =VLOOKUP(G5921,'Customer table'!A:H,8,FALSE) -> Non email user
A5922: 5921 | B5922: 3283 | C5922: 152 | D5922: 1 | E5922: 360.28 | F5922: =E5922*D5922 -> 360.28 | G5922: 5921 | H5922: =VLOOKUP(G5922,'Customer table'!A:H,8,FALSE) -> Email user
A5923: 5922 | B5923: 3284 | C5923: 47 | D5923: 3 | E5923: 1146.95 | F5923: =E5923*D5923 -> 3440.85 | G5923: 5922 | H5923: =VLOOKUP(G5923,'Customer table'!A:H,8,FALSE) -> Non email user
A5924: 5923 | B5924: 3285 | C5924: 149 | D5924: 1 | E5924: 183.34 | F5924: =E5924*D5924 -> 183.34 | G5924: 5923 | H5924: =VLOOKUP(G5924,'Customer table'!A:H,8,FALSE) -> Email user
... A9037: 9036 | B9037: 5000 | C9037: 53 | D9037: 2 | E9037: 912.95 | F9037: =E9037*D9037 -> 1825.9 | G9037: 9036 | H9037: =VLOOKUP(G9037,'Customer table'!A:H,8,FALSE) -> Non email user

Sheet Sheet5

Sheet ab_test_data
A1: customer_id | B1: variant | C1: assignment_date | D1: converted | E1: conversion_date | F1: time_to_conversion_minutes | G1: order_value | H1: device_type | K1: Metric | L1: Control (old) | M1: Variant(new)
A2: 6822 | B2: Variant | C2: 45261 | D2: 0 | H2: Mobile | K2: Users | L2: =COUNTIF(B:B,"control") -> 961 | M2: =COUNTIF(B:B,"variant") -> 1040
A3: 6314 | B3: Variant | C3: 45302 | D3: 1 | E3: 45309 | F3: 41.95 | G3: 460.05 | H3: Mobile | K3: Conversions | L3: =SUMIFS(D:D,B:B,"control") -> 153 | M3: =SUMIFS(D:D,B:B,"variant") -> 278
A4: 3345 | B4: Variant | C4: 45295 | D4: 0 | H4: Mobile | K4: Conversion rate | L4: =L3/L2 -> 0.15920916 | M4: =M3/M2 -> 0.26730769
A5: 2864 | B5: Control | C5: 45287 | D5: 0 | H5: Mobile
A6: 7773 | B6: Variant | C6: 45274 | D6: 0 | H6: Desktop | K6: 1 | L6: z score | M6: =(M4-L4)/SQRT(O11*(1-O11)*(1/L2+1/M2)) -> 5.8766964
A7: 2035 | B7: Variant | C7: 45305 | D7: 0 | H7: Tablet
A8: 753 | B8: Control | C8: 45296 | D8: 1 | E8: 45296 | F8: 15.53 | G8: 766.8 | H8: Mobile | K8: 2 | L8: p value | M8: =2*(1-_xlfn.NORM.S.DIST(ABS(M6),TRUE)) -> 4.1853476e-09
A9: 5785 | B9: Control | C9: 45264 | D9: 0 | H9: Desktop
A10: 6907 | B10: Variant | C10: 45308 | D10: 1 | E10: 45315 | F10: 32.74 | G10: 668.28 | H10: Tablet
A11: 9236 | B11: Control | C11: 45266 | D11: 0 | H11: Desktop | O11: =(L3+M3)/(M2+L2) -> 0.2153923
A12: 8423 | B12: Variant | C12: 45309 | D12: 0 | H12: Mobile
A13: 9078 | B13: Variant | C13: 45280 | D13: 0 | H13: Desktop
A14: 8547 | B14: Variant | C14: 45283 | D14: 1 | E14: 45287 | F14: 10.02 | G14: 409.24 | H14: Tablet
A15: 9284 | B15: Variant | C15: 45283 | D15: 1 | E15: 45289 | F15: 41.7 | G15: 497.97 | H15: Tablet
A16: 8657 | B16: Control | C16: 45275 | D16: 0 | H16: Desktop
A17: 4379 | B17: Variant | C17: 45317 | D17: 0 | H17: Tablet
A18: 4344 | B18: Variant | C18: 45289 | D18: 0 | H18: Desktop
A19: 6441 | B19: Control | C19: 45313 | D19: 0 | H19: Mobile
A20: 23 | B20: Control | C20: 45278 | D20: 0 | H20: Desktop
A21: 8474 | B21: Variant | C21: 45303 | D21: 0 | H21: Mobile
A22: 7856 | B22: Variant | C22: 45274 | D22: 0 | H22: Tablet
A23: 9353 | B23: Variant | C23: 45306 | D23: 0 | H23: Mobile
A24: 6076 | B24: Variant | C24: 45316 | D24: 1 | E24: 45322 | F24: 40.1 | G24: 319.01 | H24: Desktop
A25: 557 | B25: Variant | C25: 45275 | D25: 0 | H25: Desktop
A26: 2787 | B26: Control | C26: 45293 | D26: 0 | H26: Desktop
A27: 4825 | B27: Variant | C27: 45299 | D27: 0 | H27: Mobile
A28: 4370 | B28: Variant | C28: 45274 | D28: 0 | H28: Mobile
A29: 2606 | B29: Variant | C29: 45270 | D29: 0 | H29: Tablet
A30: 4420 | B30: Variant | C30: 45289 | D30: 0 | H30: Desktop
A31: 2296 | B31: Variant | C31: 45281 | D31: 1 | E31: 45285 | F31: 41.58 | G31: 869.61 | H31: Mobile
A32: 9201 | B32: Variant | C32: 45296 | D32: 0 | H32: Mobile
A33: 4538 | B33: Control | C33: 45280 | D33: 0 | H33: Desktop
A34: 3170 | B34: Control | C34: 45273 | D34: 0 | H34: Desktop
A35: 5691 | B35: Variant | C35: 45283 | D35: 0 | H35: Mobile
A36: 4760 | B36: Variant | C36: 45283 | D36: 0 | H36: Mobile
A37: 8891 | B37: Control | C37: 45309 | D37: 0 | H37: Tablet
A38: 698 | B38: Control | C38: 45311 | D38: 0 | H38: Tablet
A39: 9301 | B39: Variant | C39: 45302 | D39: 1 | E39: 45309 | F39: 7.39 | G39: 562.1 | H39: Desktop
A40: 9374 | B40: Control | C40: 45286 | D40: 0 | H40: Tablet
A41: 5803 | B41: Control | C41: 45281 | D41: 0 | H41: Desktop
A42: 940 | B42: Control | C42: 45277 | D42: 0 | H42: Desktop
A43: 217 | B43: Variant | C43: 45290 | D43: 0 | H43: Tablet
A44: 2517 | B44: Variant | C44: 45266 | D44: 0 | H44: Tablet
A45: 6332 | B45: Control | C45: 45287 | D45: 0 | H45: Desktop
A46: 6576 | B46: Control | C46: 45283 | D46: 0 | H46: Tablet
A47: 3534 | B47: Control | C47: 45311 | D47: 0 | H47: Tablet
A48: 7886 | B48: Variant | C48: 45270 | D48: 0 | H48: Tablet
A49: 8428 | B49: Control | C49: 45268 | D49: 0 | H49: Tablet
A50: 2697 | B50: Control | C50: 45321 | D50: 1 | E50: 45321 | F50: 28.98 | G50: 304.2 | H50: Desktop
A51: 3250 | B51: Control | C51: 45296 | D51: 0 | H51: Mobile
A52: 3065 | B52: Control | C52: 45267 | D52: 0 | H52: Tablet
A53: 5457 | B53: Variant | C53: 45294 | D53: 0 | H53: Mobile
A54: 1190 | B54: Variant | C54: 45265 | D54: 0 | H54: Mobile
A55: 8516 | B55: Variant | C55: 45296 | D55: 0 | H55: Tablet
A56: 6063 | B56: Control | C56: 45281 | D56: 0 | H56: Desktop
A57: 2797 | B57: Control | C57: 45305 | D57: 0 | H57: Tablet
A58: 8525 | B58: Control | C58: 45303 | D58: 1 | E58: 45307 | F58: 45 | G58: 366.08 | H58: Mobile
A59: 9661 | B59: Control | C59: 45319 | D59: 0 | H59: Mobile
A60: 49 | B60: Variant | C60: 45271 | D60: 0 | H60: Tablet
A61: 2669 | B61: Variant | C61: 45289 | D61: 0 | H61: Tablet
A62: 7440 | B62: Control | C62: 45284 | D62: 0 | H62: Desktop
A63: 3104 | B63: Variant | C63: 45300 | D63: 0 | H63: Tablet
A64: 8607 | B64: Variant | C64: 45261 | D64: 1 | E64: 45265 | F64: 2.95 | G64: 528.67 | H64: Desktop
A65: 3351 | B65: Control | C65: 45316 | D65: 0 | H65: Desktop
A66: 2444 | B66: Variant | C66: 45319 | D66: 1 | E66: 45321 | F66: 32.09 | G66: 305.91 | H66: Mobile
A67: 6754 | B67: Variant | C67: 45273 | D67: 0 | H67: Mobile
A68: 3498 | B68: Variant | C68: 45282 | D68: 0 | H68: Desktop
A69: 8242 | B69: Control | C69: 45300 | D69: 0 | H69: Tablet
A70: 5024 | B70: Control | C70: 45314 | D70: 0 | H70: Tablet
A71: 6529 | B71: Variant | C71: 45268 | D71: 0 | H71: Desktop
A72: 9273 | B72: Control | C72: 45290 | D72: 0 | H72: Mobile
A73: 2221 | B73: Control | C73: 45272 | D73: 0 | H73: Tablet
A74: 5767 | B74: Variant | C74: 45317 | D74: 0 | H74: Desktop
A75: 5841 | B75: Variant | C75: 45305 | D75: 0 | H75: Desktop
A76: 2231 | B76: Variant | C76: 45304 | D76: 0 | H76: Tablet
A77: 7540 | B77: Variant | C77: 45306 | D77: 0 | H77: Mobile
A78: 2612 | B78: Control | C78: 45294 | D78: 0 | H78: Tablet
A79: 3520 | B79: Control | C79: 45318 | D79: 1 | E79: 45319 | F79: 10.6 | G79: 253.34 | H79: Mobile
A80: 3216 | B80: Control | C80: 45302 | D80: 1 | E80: 45306 | F80: 26.52 | G80: 665.08 | H80: Tablet
A81: 5683 | B81: Control | C81: 45304 | D81: 1 | E81: 45309 | F81: 16.68 | G81: 589.96 | H81: Mobile
A82: 2177 | B82: Control | C82: 45262 | D82: 0 | H82: Desktop
A83: 4101 | B83: Control | C83: 45288 | D83: 0 | H83: Tablet
A84: 1208 | B84: Variant | C84: 45265 | D84: 0 | H84: Desktop
A85: 3217 | B85: Variant | C85: 45274 | D85: 0 | H85: Tablet
A86: 7629 | B86: Variant | C86: 45285 | D86: 0 | H86: Desktop
A87: 6196 | B87: Variant | C87: 45266 | D87: 1 | E87: 45267 | F87: 21.17 | G87: 368.13 | H87: Desktop
A88: 6812 | B88: Control | C88: 45320 | D88: 0 | H88: Desktop
A89: 3619 | B89: Variant | C89: 45314 | D89: 0 | H89: Tablet
A90: 7882 | B90: Variant | C90: 45280 | D90: 0 | H90: Mobile
A91: 2415 | B91: Control | C91: 45310 | D91: 0 | H91: Desktop
A92: 4869 | B92: Control | C92: 45319 | D92: 0 | H92: Mobile
A93: 5416 | B93: Variant | C93: 45291 | D93: 0 | H93: Mobile
A94: 4808 | B94: Variant | C94: 45268 | D94: 1 | E94: 45273 | F94: 4.58 | G94: 356.94 | H94: Desktop
A95: 1901 | B95: Control | C95: 45277 | D95: 1 | E95: 45284 | F95: 17.45 | G95: 620.69 | H95: Tablet
A96: 7172 | B96: Variant | C96: 45305 | D96: 1 | E96: 45308 | F96: 10.03 | G96: 622.71 | H96: Desktop
A97: 8558 | B97: Variant | C97: 45305 | D97: 1 | E97: 45309 | F97: 11.21 | G97: 176.24 | H97: Mobile
A98: 4148 | B98: Control | C98: 45319 | D98: 0 | H98: Tablet
A99: 6147 | B99: Variant | C99: 45265 | D99: 0 | H99: Desktop
A100: 3744 | B100: Variant | C100: 45273 | D100: 1 | E100: 45280 | F100: 31.28 | G100: 707.08 | H100: Tablet
...

Sheet transaction table
A1: order_id | B1: customer_id | C1: order_date | D1: total_amount | E1: status | F1: region | G1: payment_method
A2: 1 | B2: 799 | C2: 45110 | D2: 3291.84 | E2: Completed | F2: East | G2: Debit Card
A3: 2 | B3: 5547 | C3: 45261 | D3: 758 | E3: Completed | F3: Central | G3: Debit Card
A4: 3 | B4: 9198 | C4: 44991 | D4: 1053.57 | E4: Completed | F4: East | G4: Debit Card
A5: 4 | B5: 4722 | C5: 45146 | D5: 1936.86 | E5: Completed | F5: North | G5: Credit Card
A6: 5 | B6: 1154 | C6: 45249 | D6: 315.29 | E6: Completed | F6: North | G6: Debit Card
A7: 6 | B7: 1460 | C7: 45162 | D7: 1125.06 | E7: Completed | F7: West | G7: Debit Card
A8: 7 | B8: 1308 | C8: 45290 | D8: 2036.83 | E8: Completed | F8: West | G8: Apple Pay
A9: 8 | B9: 3308 | C9: 45227 | D9: 888.69 | E9: Completed | F9: North | G9: Debit Card
A10: 9 | B10: 2724 | C10: 45025 | D10: 14069.29 | E10: Completed | F10: East | G10: Debit Card
A11: 10 | B11: 3884 | C11: 45214 | D11: 2931.18 | E11: Completed | F11: North | G11: Debit Card
A12: 11 | B12: 1180 | C12: 45054 | D12: 1217.05 | E12: Completed | F12: Central | G12: Credit Card
A13: 12 | B13: 9183 | C13: 45131 | D13: 1082.75 | E13: Completed | F13: West | G13: Credit Card
... A17: 16 | B17: 9556 | C17: 45283 | D17: 329.52 | E17: Completed | F17: Central | G17: Debit Card
A18: 17 | B18: 799 | C18: 45279 | D18: 274.33 | E18: Completed | G18: PayPal
A19: 18 | B19: 5978 | C19: 45276 | D19: 966.66 | E19: Completed | G19: Debit Card
A20: 19 | B20: 4676 | C20: 45238 | D20: 2337.54 | E20: Completed | F20: South | G20: Credit Card
A21: 20 | B21: 4057 | C21: 45150 | D21: 973.32 | E21: Completed | F21: East | G21: Debit Card
A22: 21 | B22: 2428 | C22: 45105 | D22: 613.75 | E22: Completed | F22: East | G22: Apple Pay
A23: 22 | B23: 3514 | C23: 45285 | D23: 282.13 | E23: Completed | F23: South | G23: Apple Pay
A24: 23 | B24: 9743 | C24: 45120 | D24: 2362.58 | E24: Completed | F24: East | G24: Apple Pay
A25: 24 | B25: 4501 | C25: 44930 | D25: 340.47 | E25: Returned | F25: South | G25: Apple Pay
A26: 25 | B26: 9749 | C26: 45168 | D26: 436.2 | E26: Completed | F26: West | G26: Debit Card
A27: 26 | B27: 9799 | C27: 44961 | D27: 1417.1 | E27: Completed | F27: Central | G27: Apple Pay
A28: 27 | B28: 4031 | C28: 45119 | D28: 307.6 | E28: Completed | F28: South | G28: PayPal
A29: 28 | B29: 6404 | C29: 45209 | D29: 1393.02 | E29: Cancelled | F29: East | G29: Apple Pay
A30: 29 | B30: 6151 | C30: 45117 | D30: 1125.13 | E30: Completed | G30: Credit Card
A31: 30 | B31: 3505 | C31: 45263 | D31: 319.84 | E31: Completed | F31: West | G31: Debit Card
A32: 31 | B32: 2726 | C32: 45037 | D32: 143.55 | E32: Completed | F32: South | G32: Credit Card
A33: 32 | B33: 4985 | C33: 45038 | D33: 606.49 | E33: Completed | F33: West | G33: Apple Pay
A34: 33 | B34: 537 | C34: 45137 | D34: 4384.92 | E34: Completed | F34: West | G34: Apple Pay
A35: 34 | B35: 2445 | C35: 45188 | D35: 623.26 | E35: Completed | F35: West | G35: Debit Card
A36: 35 | B36: 9082 | C36: 45110 | D36: 189.69 | E36: Completed | F36: West | G36: Apple Pay
A37: 36 | B37: 5591 | C37: 45246 | D37: 415.12 | E37: Completed | F37: West | G37: Debit Card
A38: 37 | B38: 5023 | C38: 45253 | D38: 678.18 | E38: Completed | F38: South | G38: PayPal
A39: 38 | B39: 8865 | C39: 45176 | D39: 413.05 | E39: Completed | F39: East | G39: Debit Card
A40: 39 | B40: 6670 | C40: 45040 | D40: 292.39 | E40: Completed | F40: West | G40: Credit Card
A41: 40 | B41: 5687 | C41: 45076 | D41: 1495.64 | E41: Completed | F41: North | G41: PayPal
A42: 41 | B42: 9437 | C42: 45030 | D42: 2453.45 | E42: Completed | F42: South | G42: PayPal
... A281: 280 | B281: 5332 | C281: 45117 | D281: 377.58 | E281: Completed | F281: West | G281: PayPal
A282: 281 | B282: 1320 | C282: 45244 | D282: 1638.51 | E282: Completed | G282: PayPal
A283: 282 | B283: 8251 | C283: 45094 | D283: 1657.78 | E283: Completed | F283: East | G283: Credit Card
A284: 283 | B284: 9402 | C284: 45246 | D284: 430.26 | E284: Completed | F284: Central | G284: Apple Pay
A285: 284 | B285: 157 | C285: 44953 | D285: 492.32 | E285: Completed | F285: South | G285: PayPal
A286: 285 | B286: 4732 | C286: 45065 | D286: 1008.02 | E286: Completed | F286: North | G286: Debit Card
A287: 286 | B287: 9023 | C287: 45228 | D287: 496.71 | E287: Completed | F287: East | G287: Apple Pay
A288: 287 | B288: 4783 | C288: 45141 | D288: 2054.57 | E288: Completed | F288: West | G288: Debit Card
A289: 288 | B289: 5743 | C289: 44983 | D289: 2249.68 | E289: Completed | F289: North | G289: Apple Pay
A290: 289 | B290: 9541 | C290: 45183 | D290: 1426.12 | E290: Completed | F290: East | G290: Apple Pay
A291: 290 | B291: 5053 | C291: 44983 | D291: 1576.62 | E291: Completed | F291: South | G291: Debit Card
A292: 291 | B292: 7343 | C292: 44930 | D292: 2494.02 | E292: Completed | F292: North | G292: Debit Card
A293: 292 | B293: 9000 | C293: 45276 | D293: 149.63 | E293: Completed | F293: South | G293: Credit Card
A294: 293 | B294: 4689 | C294: 45125 | D294: 951.28 | E294: Completed | F294: North | G294: Credit Card
... A297: 296 | B297: 5426 | C297: 44937 | D297: 476.27 | E297: Completed | F297: East | G297: Apple Pay
A298: 297 | B298: 4242 | C298: 45050 | D298: 1527.31 | E298: Completed | G298: Debit Card
A299: 298 | B299: 9080 | C299: 45223 | D299: 3525.04 | E299: Completed | F299: West | G299: Credit Card
A300: 299 | B300: 4612 | C300: 45174 | D300: 1404.52 | E300: Completed | F300: South | G300: Credit Card
A301: 300 | B301: 7977 | C301: 45121 | D301: 3095.87 | E301: Completed | F301: North | G301: PayPal
A302: 301 | B302: 8114 | C302: 45290 | D302: 414.51 | E302: Completed | F302: West | G302: Debit Card
A303: 302 | B303: 951 | C303: 45209 | D303: 871.51 | E303: Completed | F303: West | G303: PayPal
A304: 303 | B304: 7355 | C304: 45120 | D304: 1450.88 | E304: Completed | F304: Central | G304: Apple Pay
A305: 304 | B305: 7091 | C305: 44982 | D305: 2114.31 | E305: Completed | F305: West | G305: Credit Card
A306: 305 | B306: 9308 | C306: 45223 | D306: 296.31 | E306: Completed | F306: Central | G306: PayPal
A307: 306 | B307: 171 | C307: 44979 | D307: 953.26 | E307: Completed | F307: East | G307: PayPal
A308: 307 | B308: 4479 | C308: 45236 | D308: 140.76 | E308: Completed | F308: North | G308: Debit Card
A309: 308 | B309: 2133 | C309: 45052 | D309: 2239.79 | E309: Completed | F309: South | G309: Debit Card
A310: 309 | B310: 3385 | C310: 45004 | D310: 3161.05 | E310: Completed | F310: North | G310: PayPal
... A398: 397 | B398: 7183 | C398: 44945 | D398: 88.32 | E398: Completed | F398: North | G398: Debit Card
A399: 398 | B399: 344 | C399: 45003 | D399: 3110.11 | E399: Returned | G399: PayPal
A400: 399 | B400: 4508 | C400: 44975 | D400: 274.33 | E400: Completed | F400: Central | G400: Debit Card
A401: 400 | B401: 6946 | C401: 45140 | D401: 154.28 | E401: Completed | F401: South | G401: Apple Pay
A402: 401 | B402: 1730 | C402: 45212 | D402: 2637.59 | E402: Completed | F402: Central | G402: Debit Card
A403: 402 | B403: 266 | C403: 45181 | D403: 644.28 | E403: Completed | F403: East | G403: Debit Card
A404: 403 | B404: 7472 | C404: 45259 | D404: 207.19 | E404: Completed | F404: West | G404: Debit Card
A405: 404 | B405: 4834 | C405: 45020 | D405: 3639.15 | E405: Completed | F405: West | G405: PayPal
A406: 405 | B406: 5691 | C406: 45113 | D406: 154.02 | E406: Completed | F406: Central | G406: Apple Pay
A407: 406 | B407: 8017 | C407: 45232 | D407: 1352.34 | E407: Completed | G407: Debit Card
A408: 407 | B408: 6965 | C408: 45242 | D408: 1737.24 | E408: Returned | F408: North | G408: Credit Card
A409: 408 | B409: 1627 | C409: 45262 | D409: 613.75 | E409: Completed | F409: East | G409: Credit Card
A410: 409 | B410: 8231 | C410: 45138 | D410: 2252.67 | E410: Completed | F410: West | G410: Debit Card
A411: 410 | B411: 9546 | C411: 45188 | D411: 1814.64 | E411: Completed | F411: East | G411: Debit Card
A412: 411 | B412: 8963 | C412: 44957 | D412: 6922.31 | E412: Completed | F412: South | G412: PayPal
A413: 412 | B413: 2184 | C413: 45164 | D413: 935.66 | E413: Completed | F413: East | G413: Credit Card
A414: 413 | B414: 1252 | C414: 45256 | D414: 2731.92 | E414: Completed | F414: South | G414: Debit Card
A415: 414 | B415: 3282 | C415: 45221 | D415: 211.3 | E415: Completed | F415: North | G415: Apple Pay
A416: 415 | B416: 7148 | C416: 45160 | D416: 255.79 | E416: Completed | F416: South | G416: Apple Pay
A417: 416 | B417: 6710 | C417: 44996 | D417: 1992.18 | E417: Completed | F417: South | G417: PayPal
A418: 417 | B418: 6325 | C418: 45274 | D418: 1675.49 | E418: Completed | F418: North | G418: Debit Card
A419: 418 | B419: 4288 | C419: 45203 | D419: 313.65 | E419: Completed | F419: Central | G419: Apple Pay
... A458: 457 | B458: 7493 | C458: 45221 | D458: 2704.9 | E458: Returned | F458: East | G458: Debit Card
A459: 458 | B459: 5552 | C459: 45255 | D459: 1651.23 | E459: Completed | G459: PayPal
A460: 459 | B460: 8128 | C460: 44965 | D460: 621.26 | E460: Cancelled | F460: North | G460: Apple Pay
A461: 460 | B461: 1777 | C461: 45211 | D461: 580 | E461: Completed | F461: Central | G461: Credit Card
A462: 461 | B462: 5119 | C462: 45241 | D462: 798.94 | E462: Completed | F462: North | G462: PayPal
A463: 462 | B463: 9369 | C463: 45103 | D463: 1064.65 | E463: Completed | F463: West | G463: Apple Pay
A464: 463 | B464: 7074 | C464: 45258 | D464: 201.88 | E464: Completed | F464: South | G464: Debit Card
A465: 464 | B465: 6743 | C465: 45221 | D465: 3034.04 | E465: Completed | F465: Central | G465: Credit Card
A466: 465 | B466: 488 | C466: 45127 | D466: 2062.23 | E466: Cancelled | F466: West | G466: Apple Pay
A467: 466 | B467: 8722 | C467: 45064 | D467: 1946.8 | E467: Completed | F467: West | G467: Apple Pay
A468: 467 | B468: 1069 | C468: 44978 | D468: 1796.44 | E468: Completed | F468: North | G468: Apple Pay
...

Sheet Coorelation
B1: PIVOT TABLE OF ORDER_ITEMS
A3: Row Labels | B3: Sum of Total revenue | C3: Sum of unit_price | D3: total_amount | H3: correlation between price and sales
A4: 1 | B4: 193.8 | C4: 193.8 | D4: =VLOOKUP(A4,'transaction table'!A:D,4,FALSE) -> 3291.84 | H4: =CORREL(C4:C5003,D4:D5003) -> 0.012274773
A5: 2 | B5: 791.04 | C5: 395.52 | D5: =VLOOKUP(A5,'transaction table'!A:D,4,FALSE) -> 758
A6: 3 | B6: 2307 | C6: 1153.5 | D6: =VLOOKUP(A6,'transaction table'!A:D,4,FALSE) -> 1053.57
A7: 4 | B7: 318.02 | C7: 318.02 | D7: =VLOOKUP(A7,'transaction table'!A:D,4,FALSE) -> 1936.86
A8: 5 | B8: 159.37 | C8: 159.37 | D8: =VLOOKUP(A8,'transaction table'!A:D,4,FALSE) -> 315.29
A9: 6 | B9: 280.61 | C9: 280.61 | D9: =VLOOKUP(A9,'transaction table'!A:D,4,FALSE) -> 1125.06
A10: 7 | B10: 628.59 | C10: 628.59 | D10: =VLOOKUP(A10,'transaction table'!A:D,4,FALSE) -> 2036.83
A11: 8 | B11: 228.45 | C11: 228.45 | D11: =VLOOKUP(A11,'transaction table'!A:D,4,FALSE) -> 888.69
A12: 9 | B12: 196.53 | C12: 196.53 | D12: =VLOOKUP(A12,'transaction table'!A:D,4,FALSE) -> 14069.29
A13: 10 | B13: 1936.86 | C13: 968.43 | D13: =VLOOKUP(A13,'transaction table'!A:D,4,FALSE) -> 2931.18
A14: 11 | B14: 315.29 | C14: 315.29 | D14: =VLOOKUP(A14,'transaction table'!A:D,4,FALSE) -> 1217.05
A15: 12 | B15: 579.6 | C15: 579.6 | D15: =VLOOKUP(A15,'transaction table'!A:D,4,FALSE) -> 1082.75
A16: 13 | B16: 545.46 | C16: 545.46 | D16: =VLOOKUP(A16,'transaction table'!A:D,4,FALSE) -> 256.17
... A5003: 5000 | B5003: 492.52 | C5003: 246.26 | D5003: =VLOOKUP(A5003,'transaction table'!A:D,4,FALSE) -> 2575.5
A5004: 5001 | B5004: 977.28 | C5004: 325.76
A5005: 5002 | B5005: 971.06 | C5005: 971.06
A5006: 5003 | B5006: 923.6 | C5006: 923.6
A5007: 5004 | B5007: 674.62 | C5007: 337.31
A5008: 5005 | B5008: 580.8 | C5008: 193.6
A5009: 5006 | B5009: 681.96 | C5009: 340.98
A5010: 5007 | B5010: 397.78 | C5010: 198.89
A5011: 5008 | B5011: 2899.98 | C5011: 966.66
A5012: 5009 | B5012: 526.08 | C5012: 526.08
A5013: 5010 | B5013: 471.55 | C5013: 471.55
A5014: 5011 | B5014: 775.98 | C5014: 258.66
A5015: 5012 | B5015: 287.09 | C5015: 287.09
... A9039: 9036 | B9039: 1825.9 | C9039: 912.95
A9040: Grand Total | B9040: 6813888 | C9040: 5421039.5

Sheet Sheet9
A3: Row Labels | B3: Count of order_id | C3: Sum of total_amount
A4: Jan | B4: 338 | C4: 507305.33 | E4: 338 | F4: 507305.33
A5: Feb | B5: 335 | C5: 445728.02 | E5: 335 | F5: 445728.02
A6: Mar | B6: 329 | C6: 433758.49 | E6: 329 | F6: 433758.49
A7: Apr | B7: 354 | C7: 534749.64 | E7: 354 | F7: 534749.64
A8: May | B8: 323 | C8: 444439.87 | E8: 323 | F8: 444439.87
A9: Jun | B9: 319 | C9: 463807.62 | E9: 319 | F9: 463807.62
A10: Jul | B10: 395 | C10: 519507.33 | E10: 395 | F10: 519507.33
A11: Aug | B11: 408 | C11: 581251.13 | E11: 408 | F11: 581251.13
A12: Sep | B12: 357 | C12: 534730.19 | E12: 357 | F12: 534730.19
A13: Oct | B13: 498 | C13: 680839.77 | E13: 498 | F13: 680839.77
A14: Nov | B14: 665 | C14: 921551.1 | E14: 665 | F14: 921551.1
A15: Dec | B15: 679 | C15: 997196.38 | E15: 679 | F15: 997196.38
A16: Grand Total | B16: 5000 | C16: 7064864.9

Sheet Linear Regression
A1: SUMMARY OUTPUT
A3: Regression Statistics
A4: Multiple R | B4: 0.98973792 | L4: R Square | M4: 0.97958115
A5: R Square | B5: 0.97958115
A6: Adjusted R Square | B6: 0.97731239
A7: Standard Error | B7: 29248.352
A8: Observations | B8: 11
A10: ANOVA
B11: df | C11: SS | D11: MS | E11: F | F11: Significance F
A12: Regression | B12: 1 | C12: 3.6936395e+11 | D12: 3.6936395e+11 | E12: 431.76925 | F12: 6.4800749e-09
A13: Residual | B13: 9 | C13: 7.6991949e+09 | D13: 8.554661e+08
A14: Total | B14: 10 | C14: 3.7706315e+11
B16: Coefficients | C16: Standard Error | D16: t Stat | E16: P-value | F16: Lower 95% | G16: Upper 95% | H16: Lower 95.0% | I16: Upper 95.0%
A17: Intercept | B17: -15682.089 | C17: 30736.522 | D17: -0.51021026 | E17: 0.62218103 | F17: -85212.931 | G17: 53848.754 | H17: -85212.931 | I17: 53848.754
A18: 338 | B18: 1443.5999 | C18: 69.473787 | D18: 20.779058 | E18: 6.4800749e-09 | F18: 1286.4392 | G18: 1600.7605 | H18: 1286.4392 | I18: 1600.7605
