Workbook

Sheet Transaction table
B1: TRANSACTION TABLE
A2: order_id | B2: customer_id | C2: order_date | D2: total_amount | E2: status | F2: region | G2: payment_method | H2: product_id | I2: product_name
A3: 1 | B3: 799 | C3: 45110 | D3: 3291.84 | E3: Completed | F3: East | G3: Debit Card | H3: 1 | I3: =VLOOKUP(H3,Product!A:B,2,FALSE) -> Dell Laptop Model 1
A4: 2 | B4: 5547 | C4: 45261 | D4: 3291.84 | E4: Completed | F4: Central | G4: Debit Card | H4: 2 | I4: =VLOOKUP(H4,Product!A:B,2,FALSE) -> HP Laptop Model 2
A5: 3 | B5: 9198 | C5: 44991 | D5: 3291.84 | E5: Completed | F5: East | G5: Debit Card | H5: 3 | I5: =VLOOKUP(H5,Product!A:B,2,FALSE) -> ASUS Laptop Model 3
A6: 4 | B6: 4722 | C6: 45146 | D6: 3291.84 | E6: Completed | F6: North | G6: Credit Card | H6: 4 | I6: =VLOOKUP(H6,Product!A:B,2,FALSE) -> Dell Laptop Model 4
A7: 5 | B7: 1154 | C7: 45249 | D7: 3291.84 | E7: Completed | F7: North | G7: Debit Card | H7: 5 | I7: =VLOOKUP(H7,Product!A:B,2,FALSE) -> ASUS Laptop Model 5
A8: 6 | B8: 1460 | C8: 45162 | D8: 3291.84 | E8: Completed | F8: West | G8: Debit Card | H8: 6 | I8: =VLOOKUP(H8,Product!A:B,2,FALSE) -> ASUS Laptop Model 6
A9: 7 | B9: 1308 | C9: 45290 | D9: 3291.84 | E9: Completed | F9: West | G9: Apple Pay | H9: 7 | I9: =VLOOKUP(H9,Product!A:B,2,FALSE) -> Lenovo Laptop Model 7
A10: 8 | B10: 3308 | C10: 45227 | D10: 3291.84 | E10: Completed | F10: North | G10: Debit Card | H10: 8 | I10: =VLOOKUP(H10,Product!A:B,2,FALSE) -> HP Laptop Model 8
A11: 9 | B11: 2724 | C11: 45025 | D11: 3291.84 | E11: Completed | F11: East | G11: Debit Card | H11: 9 | I11: =VLOOKUP(H11,Product!A:B,2,FALSE) -> HP Laptop Model 9
A12: 10 | B12: 3884 | C12: 45214 | D12: 3291.84 | E12: Completed | F12: North | G12: Debit Card | H12: 10 | I12: =VLOOKUP(H12,Product!A:B,2,FALSE) -> Dell Laptop Model 10
A13: 11 | B13: 1180 | C13: 45054 | D13: 3291.84 | E13: Completed | F13: Central | G13: Credit Card | H13: 11 | I13: =VLOOKUP(H13,Product!A:B,2,FALSE) -> Lenovo Laptop Model 11
A14: 12 | B14: 9183 | C14: 45131 | D14: 3291.84 | E14: Completed | F14: West | G14: Credit Card | H14: 12 | I14: =VLOOKUP(H14,Product!A:B,2,FALSE) -> Apple Laptop Model 12
... A202: 200 | B202: 651 | C202: 45041 | D202: 3291.84 | E202: Completed | F202: West | G202: Apple Pay | H202: 200 | I202: =VLOOKUP(H202,Product!A:B,2,FALSE) -> Garmin Smartwatche Model 40
A203: 201 | B203: 731 | C203: 45149 | D203: 3291.84 | E203: Completed | F203: East | G203: Apple Pay
A204: 202 | B204: 2296 | C204: 45250 | D204: 3291.84 | E204: Completed | F204: Central | G204: PayPal
A205: 203 | B205: 2754 | C205: 44989 | D205: 3291.84 | E205: Completed | F205: South | G205: Debit Card
A206: 204 | B206: 2145 | C206: 45232 | D206: 3291.84 | E206: Completed | F206: West | G206: Credit Card
A207: 205 | B207: 1562 | C207: 45229 | D207: 3291.84 | E207: Completed | F207: Central | G207: Credit Card
A208: 206 | B208: 7148 | C208: 45106 | D208: 3291.84 | E208: Completed | F208: South | G208: Credit Card
A209: 207 | B209: 2966 | C209: 45018 | D209: 3291.84 | E209: Returned | F209: Central | G209: Credit Card
A210: 208 | B210: 9250 | C210: 45163 | D210: 3291.84 | E210: Completed | F210: East | G210: Credit Card
A211: 209 | B211: 3412 | C211: 45006 | D211: 3291.84 | E211: Cancelled | F211: West | G211: PayPal
A212: 210 | B212: 7717 | C212: 45026 | D212: 3291.84 | E212: Completed | F212: Central | G212: Apple Pay
A213: 211 | B213: 5927 | C213: 45197 | D213: 3291.84 | E213: Completed | F213: East | G213: Apple Pay
A214: 212 | B214: 3663 | C214: 45273 | D214: 3291.84 | E214: Completed | F214: South | G214: Debit Card
... A5002: 5000 | B5002: 863 | C5002: 45197 | D5002: 3291.84 | E5002: Completed | F5002: North | G5002: Debit Card

Sheet Sheet2
A1: order_id | B1: customer_id | C1: order_date | D1: total_amount | E1: status | F1: region | G1: payment_method | I1: Following exel functions were used
A2: 1 | B2: 799 | C2: 45110 | D2: 3291.84 | E2: Completed | F2: East | G2: Debit Card | I2: 1 | J2: Calculate total revenue
A3: 2 | B3: 5547 | C3: 45261 | D3: 758 | E3: Completed | F3: Central | G3: Debit Card | I3: ANS | J3: =SUM(D:D) -> 7064864.9
A4: 3 | B4: 9198 | C4: 44991 | D4: 1053.57 | E4: Completed | F4: East | G4: Debit Card | I4: 2 | J4: Calculate average of total amount
A5: 4 | B5: 4722 | C5: 45146 | D5: 1936.86 | E5: Completed | F5: North | G5: Credit Card | I5: ANS | J5: =AVERAGE(D:D) -> 1412.973
A6: 5 | B6: 1154 | C6: 45249 | D6: 315.29 | E6: Completed | F6: North | G6: Debit Card | I6: 3 | J6: If total amount greater than 2000 mark High otherwise Low
A7: 6 | B7: 1460 | C7: 45162 | D7: 1125.06 | E7: Completed | F7: West | G7: Debit Card | I7: ANS | J7: =IF(D2>2000,"High","Low") -> High
A8: 7 | B8: 1308 | C8: 45290 | D8: 2036.83 | E8: Completed | F8: West | G8: Apple Pay | I8: 4 | J8: How many total order are there
A9: 8 | B9: 3308 | C9: 45227 | D9: 888.69 | E9: Completed | F9: North | G9: Debit Card | I9: ANS | J9: =COUNT(A:A) -> 5000
A10: 9 | B10: 2724 | C10: 45025 | D10: 14069.29 | E10: Completed | F10: East | G10: Debit Card | I10: 5 | J10: How many order are from West Region
A11: 10 | B11: 3884 | C11: 45214 | D11: 2931.18 | E11: Completed | F11: North | G11: Debit Card | I11: ANS | J11: =COUNTIF(F:F,"West") -> 1099
A12: 11 | B12: 1180 | C12: 45054 | D12: 1217.05 | E12: Completed | F12: Central | G12: Credit Card | I12: 6 | J12: Find highest order value
A13: 12 | B13: 9183 | C13: 45131 | D13: 1082.75 | E13: Completed | F13: West | G13: Credit Card | I13: ANS | J13: =MAX(D:D) -> 29817.33
A14: 13 | B14: 7875 | C14: 45182 | D14: 256.17 | E14: Completed | F14: North | G14: Apple Pay | I14: 7 | J14: Find lowest order value
A15: 14 | B15: 7610 | C15: 45135 | D15: 827.49 | E15: Completed | F15: Central | G15: Credit Card | I15: ANS | J15: =MIN(D:D) -> 28.09
A16: 15 | B16: 4366 | C16: 45128 | D16: 1814.82 | E16: Completed | F16: South | G16: Credit Card | I16: 8 | J16: Convert region to uppercase
A17: 16 | B17: 9556 | C17: 45283 | D17: 329.52 | E17: Completed | F17: Central | G17: Debit Card | I17: ANS | J17: =UPPER(F2) -> EAST
A18: 17 | B18: 799 | C18: 45279 | D18: 274.33 | E18: Completed | F18: others | G18: PayPal | I18: 9 | J18: Find region using order id
A19: 18 | B19: 5978 | C19: 45276 | D19: 966.66 | E19: Completed | F19: others | G19: Debit Card | I19: ANS | J19: =VLOOKUP(A6,A:G,6,FALSE) -> North
A20: 19 | B20: 4676 | C20: 45238 | D20: 2337.54 | E20: Completed | F20: South | G20: Credit Card | I20: 10 | J20: Total revenue from completed orders only
A21: 20 | B21: 4057 | C21: 45150 | D21: 973.32 | E21: Completed | F21: East | G21: Debit Card | I21: ANS | J21: =SUMIF(E:E,"Completed",D:D) -> 6741715.9
A22: 21 | B22: 2428 | C22: 45105 | D22: 613.75 | E22: Completed | F22: East | G22: Apple Pay
A23: 22 | B23: 3514 | C23: 45285 | D23: 282.13 | E23: Completed | F23: South | G23: Apple Pay
A24: 23 | B24: 9743 | C24: 45120 | D24: 2362.58 | E24: Completed | F24: East | G24: Apple Pay
A25: 24 | B25: 4501 | C25: 44930 | D25: 340.47 | E25: Returned | F25: South | G25: Apple Pay
A26: 25 | B26: 9749 | C26: 45168 | D26: 436.2 | E26: Completed | F26: West | G26: Debit Card
A27: 26 | B27: 9799 | C27: 44961 | D27: 1417.1 | E27: Completed | F27: Central | G27: Apple Pay
A28: 27 | B28: 4031 | C28: 45119 | D28: 307.6 | E28: Completed | F28: South | G28: PayPal
A29: 28 | B29: 6404 | C29: 45209 | D29: 1393.02 | E29: Cancelled | F29: East | G29: Apple Pay
A30: 29 | B30: 6151 | C30: 45117 | D30: 1125.13 | E30: Completed | F30: others | G30: Credit Card
A31: 30 | B31: 3505 | C31: 45263 | D31: 319.84 | E31: Completed | F31: West | G31: Debit Card
A32: 31 | B32: 2726 | C32: 45037 | D32: 143.55 | E32: Completed | F32: South | G32: Credit Card
A33: 32 | B33: 4985 | C33: 45038 | D33: 606.49 | E33: Completed | F33: West | G33: Apple Pay
... A5001: 5000 | B5001: 863 | C5001: 45197 | D5001: 2575.5 | E5001: Completed | F5001: North | G5001: Debit Card

Sheet Sheet3
C1: MONTHLY REVENUE BY REGIONS
A3: Sum of total_amount | B3: Column Labels
A4: Row Labels | B4: Central | C4: East | D4: North | E4: others | F4: South | G4: West | H4: Grand Total
A5: Jan | B5: 102501.09 | C5: 70384.14 | D5: 102975.45 | E5: 7026 | F5: 105939.77 | G5: 118478.88 | H5: 507305.33
A6: Feb | B6: 80622.8 | C6: 75136.97 | D6: 81941.87 | E6: 7678.99 | F6: 81998.11 | G6: 118349.28 | H6: 445728.02
A7: Mar | B7: 92477.49 | C7: 80018.05 | D7: 63644.06 | E7: 6892.42 | F7: 103116.55 | G7: 87609.92 | H7: 433758.49
A8: Apr | B8: 134736.84 | C8: 117374.19 | D8: 88110.46 | E8: 8288.8 | F8: 98375.98 | G8: 87863.37 | H8: 534749.64
A9: May | B9: 81451.28 | C9: 78508.84 | D9: 84399.48 | E9: 11517.08 | F9: 96024.06 | G9: 92539.13 | H9: 444439.87
A10: Jun | B10: 77368.17 | C10: 93012.96 | D10: 110214.76 | E10: 8286.18 | F10: 105171.26 | G10: 69754.29 | H10: 463807.62
A11: Jul | B11: 93773.22 | C11: 105478.92 | D11: 85198.32 | E11: 18069.42 | F11: 84452.33 | G11: 132535.12 | H11: 519507.33
A12: Aug | B12: 110596.88 | C12: 101920.48 | D12: 119535.7 | E12: 11912.19 | F12: 122794.14 | G12: 114491.74 | H12: 581251.13
A13: Sep | B13: 105173.13 | C13: 122048.7 | D13: 96011.18 | E13: 16197.33 | F13: 75629.6 | G13: 119670.25 | H13: 534730.19
A14: Oct | B14: 100475.42 | C14: 168461.16 | D14: 124729.14 | E14: 12614.36 | F14: 121918.26 | G14: 152641.43 | H14: 680839.77
A15: Nov | B15: 158362.87 | C15: 175393.78 | D15: 160933.04 | E15: 13821.77 | F15: 210010.93 | G15: 203028.71 | H15: 921551.1
A16: Dec | B16: 169084.81 | C16: 224044.19 | D16: 170392.02 | E16: 25472.02 | F16: 193786.45 | G16: 214416.89 | H16: 997196.38
A17: Grand Total | B17: 1306624 | C17: 1411782.4 | D17: 1288085.5 | E17: 147776.56 | F17: 1399217.4 | G17: 1511379 | H17: 7064864.9

Sheet Product
A1: product_id | B1: product_name | C1: category | D1: brand | E1: price | F1: cost | G1: profit_margin
A2: 1 | B2: Dell Laptop Model 1 | C2: Laptops | D2: Dell | E2: 440.02 | F2: 260.16 | G2: 40.88
A3: 2 | B3: HP Laptop Model 2 | C3: Laptops | D3: HP | E3: 623.26 | F3: 352.38 | G3: 43.46
A4: 3 | B4: ASUS Laptop Model 3 | C4: Laptops | D4: ASUS | E4: 539.1 | F4: 330.62 | G4: 38.67
A5: 4 | B5: Dell Laptop Model 4 | C5: Laptops | D5: Dell | E5: 549.91 | F5: 321.64 | G5: 41.51
A6: 5 | B6: ASUS Laptop Model 5 | C6: Laptops | D6: ASUS | E6: 442.46 | F6: 256.55 | G6: 42.02
A7: 6 | B7: ASUS Laptop Model 6 | C7: Laptops | D7: ASUS | E7: 1071.23 | F7: 661.36 | G7: 38.26
A8: 7 | B8: Lenovo Laptop Model 7 | C8: Laptops | D8: Lenovo | E8: 1695.09 | F8: 933.95 | G8: 44.9
A9: 8 | B9: HP Laptop Model 8 | C9: Laptops | D9: HP | E9: 1517.02 | F9: 911.79 | G9: 39.9
A10: 9 | B10: HP Laptop Model 9 | C10: Laptops | D10: HP | E10: 744.5 | F10: 494.74 | G10: 33.55
A11: 10 | B11: Dell Laptop Model 10 | C11: Laptops | D11: Dell | E11: 548.39 | F11: 309.57 | G11: 43.55
A12: 11 | B12: Lenovo Laptop Model 11 | C12: Laptops | D12: Lenovo | E12: 1365.96 | F12: 916.65 | G12: 32.89
A13: 12 | B13: Apple Laptop Model 12 | C13: Laptops | D13: Apple | E13: 1257.96 | F13: 875.5 | G13: 30.4
... A201: 200 | B201: Garmin Smartwatche Model 40 | C201: Smartwatches | D201: Garmin | E201: 105.06 | F201: 64.4 | G201: 38.7

Sheet  Dashboard 1
A9: Row Labels | B9: Sum of total_amount
A10: Jan | B10: 1112641.9
A11: Feb | B11: 1102766.4
A12: Mar | B12: 1083015.4
A13: Apr | B13: 1165311.4
A14: May | B14: 1063264.3
A15: Jun | B15: 1050097
A16: Jul | B16: 1300276.8
A17: Aug | B17: 1343070.7
A18: Sep | B18: 1175186.9
A19: Oct | B19: 1639336.3
A20: Nov | B20: 2189073.6
A21: Dec | B21: 2235159.4
A22: Grand Total | B22: 16459200
A24: =SUM(B10:B21) -> 16459200

Sheet Dashboard 2
A3: Row Labels | B3: Sum of total_amount
A4: Apple Headphone Model 18 | B4: 4140.13
A5: Apple Laptop Model 33 | B5: 4384.92
A6: Bose Headphone Model 26 | B6: 8831.2
A7: HP Laptop Model 9 | B7: 14069.29
A8: Samsung Smartphone Model 31 | B8: 8984.9
A9: Grand Total | B9: 40410.44
